README.md
setup.py
ViNeSeg_Stroh.egg-info/PKG-INFO
ViNeSeg_Stroh.egg-info/SOURCES.txt
ViNeSeg_Stroh.egg-info/dependency_links.txt
ViNeSeg_Stroh.egg-info/entry_points.txt
ViNeSeg_Stroh.egg-info/requires.txt
ViNeSeg_Stroh.egg-info/top_level.txt
vineseg_Stroh/__init__.py
vineseg_Stroh/__main__.py
vineseg_Stroh/app.py
vineseg_Stroh/label_file.py
vineseg_Stroh/logger.py
vineseg_Stroh/modelmanager.py
vineseg_Stroh/shape.py
vineseg_Stroh/testing.py
vineseg_Stroh/ai_pipeline/DataLoader.py
vineseg_Stroh/ai_pipeline/Img_190118.png
vineseg_Stroh/ai_pipeline/Img_190118_curr.png
vineseg_Stroh/ai_pipeline/Img_190131.png
vineseg_Stroh/ai_pipeline/Img_4266.png
vineseg_Stroh/ai_pipeline/Img_4512.png
vineseg_Stroh/ai_pipeline/Readme.md
vineseg_Stroh/ai_pipeline/add_channels.py
vineseg_Stroh/ai_pipeline/config_finetuning_identity_unet.json
vineseg_Stroh/ai_pipeline/config_finetuning_segresnet.json
vineseg_Stroh/ai_pipeline/config_prediction.json
vineseg_Stroh/ai_pipeline/config_prediction_transformer.json
vineseg_Stroh/ai_pipeline/config_pretrainig_identity_unet.json
vineseg_Stroh/ai_pipeline/config_pretraining_segresnet.json
vineseg_Stroh/ai_pipeline/config_pretraining_unet.json
vineseg_Stroh/ai_pipeline/config_training.json
vineseg_Stroh/ai_pipeline/config_training_original.json
vineseg_Stroh/ai_pipeline/convert_labelme_to_image.py
vineseg_Stroh/ai_pipeline/env_inference.yml
vineseg_Stroh/ai_pipeline/framework_bench.py
vineseg_Stroh/ai_pipeline/generate_test_data.py
vineseg_Stroh/ai_pipeline/image_interpolation.py
vineseg_Stroh/ai_pipeline/monai_models.py
vineseg_Stroh/ai_pipeline/postprocessing.py
vineseg_Stroh/ai_pipeline/prediction.py
vineseg_Stroh/ai_pipeline/prediction_bench.py
vineseg_Stroh/ai_pipeline/prediction_development.py
vineseg_Stroh/ai_pipeline/preprocessing_augmentation.py
vineseg_Stroh/ai_pipeline/save_preprocessed_images.py
vineseg_Stroh/ai_pipeline/segmentation_main.py
vineseg_Stroh/ai_pipeline/training.py
vineseg_Stroh/ai_pipeline/util.py
vineseg_Stroh/cli/__init__.py
vineseg_Stroh/cli/draw_json.py
vineseg_Stroh/cli/draw_label_png.py
vineseg_Stroh/cli/json_to_dataset.py
vineseg_Stroh/cli/on_docker.py
vineseg_Stroh/config/__init__.py
vineseg_Stroh/config/default_config.yaml
