Metadata-Version: 2.1
Name: ViNeSeg-Stroh
Version: 0.0.30
Summary: Image Polygonal Annotation with Python
Home-page: UNKNOWN
Author: Nicolas Ruffini
Author-email: nicolas.ruffini@lir-mainz.de
License: GPLv3
Keywords: Image Annotation,Machine Learning
Platform: UNKNOWN
Classifier: Intended Audience :: Developers
Classifier: Natural Language :: English
Classifier: Programming Language :: Python
Classifier: Programming Language :: Python :: 3.7
Classifier: Programming Language :: Python :: Implementation :: CPython
Classifier: Programming Language :: Python :: Implementation :: PyPy
